zWebApi/__init__.py
zWebApi/app.py
zWebApi/exceptions.py
zWebApi/logger.py
zWebApi/signature_enforcer.py
zWebApi/utils.py
zWebApi/tools/__init__.py
zWebApi/tools/db/__init__.py
zWebApi/tools/db/ormsql.py
zWebApi/tools/db/z_zookeeper.py
zWebApi/tools/db/zmysql.py
zWebApi/tools/db/zredis.py
zwebapi-1.1.0.dist-info/licenses/LICENSE
zwebapi-1.1.0.dist-info/METADATA
zwebapi-1.1.0.dist-info/WHEEL
zwebapi-1.1.0.dist-info/top_level.txt
zwebapi-1.1.0.dist-info/RECORD
